invenzi/__init__.py
invenzi-0.0.1.dist-info/licenses/LICENSE
invenzi-0.0.1.dist-info/METADATA
invenzi-0.0.1.dist-info/WHEEL
invenzi-0.0.1.dist-info/top_level.txt
invenzi-0.0.1.dist-info/RECORD
